ctxtoolkit/__init__.py
ctxtoolkit/anti_pollution.py
ctxtoolkit/context_builder.py
ctxtoolkit/py.typed
ctxtoolkit/token_saver.py
ctxtoolkit/tool_coordinator.py
ctxtoolkit-0.1.1.dist-info/licenses/LICENSE
ctxtoolkit-0.1.1.dist-info/METADATA
ctxtoolkit-0.1.1.dist-info/WHEEL
ctxtoolkit-0.1.1.dist-info/top_level.txt
ctxtoolkit-0.1.1.dist-info/RECORD
