Metadata-Version: 2.4
Name: ctxtoolkit
Version: 0.1.1
Summary: Context Engineering Toolkit - Practical tools for optimizing AI context management
Home-page: https://github.com/Abossss/python-ctxtoolkit
Author: Abossss
Author-email: 
Project-URL: Source, https://github.com/Abossss/python-ctxtoolkit
Project-URL: Issues, https://github.com/Abossss/python-ctxtoolkit/issues
Project-URL: Documentation, https://github.com/Abossss/python-ctxtoolkit/blob/main/API_DOCUMENTATION.md
Keywords: ai,context,prompt,llm,tools,context-engineering,prompt-engineering,ai-tools,large-language-models
Classifier: Development Status :: 3 - Alpha
Classifier: Intended Audience :: Developers
Classifier: License :: OSI Approved :: MIT License
Classifier: Natural Language :: English
Classifier: Programming Language :: Python :: 3
Classifier: Programming Language :: Python :: 3.7
Classifier: Programming Language :: Python :: 3.8
Classifier: Programming Language :: Python :: 3.9
Classifier: Programming Language :: Python :: 3.10
Classifier: Programming Language :: Python :: 3.11
Classifier: Programming Language :: Python :: 3.12
Classifier: Topic :: Software Development :: Libraries :: Python Modules
Classifier: Topic :: Utilities
Classifier: Typing :: Typed
Requires-Python: >=3.7
License-File: LICENSE
Provides-Extra: dev
Requires-Dist: pytest>=6.0; extra == "dev"
Requires-Dist: flake8>=3.8; extra == "dev"
Requires-Dist: black>=22.0; extra == "dev"
Requires-Dist: isort>=5.10; extra == "dev"
Requires-Dist: mypy>=0.930; extra == "dev"
Dynamic: author
Dynamic: classifier
Dynamic: description
Dynamic: description-content-type
Dynamic: home-page
Dynamic: keywords
Dynamic: license-file
Dynamic: project-url
Dynamic: provides-extra
Dynamic: requires-python
Dynamic: summary
